acquisition_plotting/__init__.py
acquisition_plotting/_version.py
acquisition_plotting/make_gif.py
acquisition_plotting/plot_bo_metrics.py
acquisition_plotting/plot_evaluations.py
acquisition_plotting/plot_lnl_hist.py
acquisition_plotting/plot_objective.py
acquisition_plotting/plot_overlaid_corner.py
acquisition_plotting/trieste.py
acquisition_plotting/utils.py
acquisition_plotting/space/__init__.py
acquisition_plotting/space/space.py
acquisition_plotting/space/transformers.py
compas_surrogate.acquisition_plotting-0.1.3.dist-info/METADATA
compas_surrogate.acquisition_plotting-0.1.3.dist-info/WHEEL
compas_surrogate.acquisition_plotting-0.1.3.dist-info/top_level.txt
compas_surrogate.acquisition_plotting-0.1.3.dist-info/RECORD
